sl_parser/__init__.py
sl_parser/logentry.py
sl_parser/logfile.py
sl_parser/unit.py
sl_parser-0.2.0.dist-info/LICENSE
sl_parser-0.2.0.dist-info/METADATA
sl_parser-0.2.0.dist-info/WHEEL
sl_parser-0.2.0.dist-info/RECORD
