Metadata-Version: 2.1
Name: sl-parser
Version: 0.2.0
Summary: 
Author: Augusto Zanellato
Author-email: augusto.zanellato@gmail.com
Requires-Python: >=3.10,<4.0
Classifier: Programming Language :: Python :: 3
Classifier: Programming Language :: Python :: 3.10
Classifier: Programming Language :: Python :: 3.11
Requires-Dist: pydantic (>=1.10.4,<2.0.0)
Requires-Dist: pydantic-computed (>=0.2.1,<0.3.0)
